<?xml version="1.0" encoding="utf-8"?>
<TextureAtlas imagePath="taeyaiminus.png">
	<!-- Created with Adobe Animate version 21.0.0.35450 -->
	<!-- http://www.adobe.com/products/animate.html -->
	<SubTexture name="taeyai2 instance 10000" x="0" y="0" width="556" height="677"/>
	<SubTexture name="taeyai2 instance 10001" x="556" y="0" width="556" height="677"/>
	<SubTexture name="taeyai2 instance 10002" x="1112" y="0" width="556" height="677"/>
	<SubTexture name="taeyai2 instance 10003" x="1668" y="0" width="556" height="677"/>
	<SubTexture name="taeyai2 instance 10004" x="2224" y="0" width="556" height="677"/>
	<SubTexture name="taeyai2 instance 10005" x="2780" y="0" width="556" height="677"/>
	<SubTexture name="taeyai2 instance 10006" x="3336" y="0" width="556" height="677"/>
	<SubTexture name="taeyai2 instance 10007" x="3892" y="0" width="556" height="677"/>
	<SubTexture name="taeyai2 instance 10008" x="4448" y="0" width="556" height="677"/>
	<SubTexture name="taeyai2 instance 10009" x="5004" y="0" width="556" height="677"/>
	<SubTexture name="taeyai2 instance 10010" x="5560" y="0" width="556" height="677"/>
	<SubTexture name="taeyai2 instance 10011" x="6116" y="0" width="556" height="677"/>
	<SubTexture name="taeyai4 instance 10000" x="6672" y="0" width="595" height="711"/>
	<SubTexture name="taeyai4 instance 10001" x="7267" y="0" width="595" height="711"/>
	<SubTexture name="taeyai4 instance 10002" x="0" y="711" width="595" height="711"/>
	<SubTexture name="taeyai4 instance 10003" x="595" y="711" width="595" height="711"/>
	<SubTexture name="taeyai4 instance 10004" x="1190" y="711" width="595" height="711"/>
	<SubTexture name="taeyai4 instance 10005" x="1785" y="711" width="595" height="711"/>
	<SubTexture name="taeyai4 instance 10006" x="2380" y="711" width="595" height="711"/>
	<SubTexture name="taeyai4 instance 10007" x="2975" y="711" width="595" height="711"/>
	<SubTexture name="taeyai4 instance 10008" x="3570" y="711" width="595" height="711"/>
	<SubTexture name="taeyai4 instance 10009" x="4165" y="711" width="595" height="711"/>
	<SubTexture name="taeyai4 instance 10010" x="4760" y="711" width="595" height="711"/>
	<SubTexture name="taeyai4 instance 10011" x="5355" y="711" width="595" height="711"/>
	<SubTexture name="taeyai5 instance 10000" x="5950" y="711" width="582" height="715"/>
	<SubTexture name="taeyai5 instance 10001" x="6532" y="711" width="582" height="715"/>
	<SubTexture name="taeyai5 instance 10002" x="7114" y="711" width="582" height="715"/>
	<SubTexture name="taeyai5 instance 10003" x="0" y="1426" width="582" height="715"/>
	<SubTexture name="taeyai5 instance 10004" x="582" y="1426" width="582" height="715"/>
	<SubTexture name="taeyai5 instance 10005" x="1164" y="1426" width="582" height="715"/>
	<SubTexture name="taeyai5 instance 10006" x="1746" y="1426" width="582" height="715"/>
	<SubTexture name="taeyai5 instance 10007" x="2328" y="1426" width="582" height="715"/>
	<SubTexture name="taeyai5 instance 10008" x="2910" y="1426" width="582" height="715"/>
	<SubTexture name="taeyai5 instance 10009" x="3492" y="1426" width="582" height="715"/>
	<SubTexture name="taeyai5 instance 10010" x="4074" y="1426" width="582" height="715"/>
	<SubTexture name="taeyai5 instance 10011" x="4656" y="1426" width="582" height="715"/>
	<SubTexture name="taeyai6 instance 10000" x="5238" y="1426" width="579" height="691"/>
	<SubTexture name="taeyai6 instance 10001" x="5817" y="1426" width="579" height="691"/>
	<SubTexture name="taeyai6 instance 10002" x="6396" y="1426" width="579" height="691"/>
	<SubTexture name="taeyai6 instance 10003" x="6975" y="1426" width="579" height="691"/>
	<SubTexture name="taeyai6 instance 10004" x="7554" y="1426" width="579" height="691"/>
	<SubTexture name="taeyai6 instance 10005" x="0" y="2141" width="579" height="691"/>
	<SubTexture name="taeyai6 instance 10006" x="579" y="2141" width="579" height="691"/>
	<SubTexture name="taeyai6 instance 10007" x="1158" y="2141" width="579" height="691"/>
	<SubTexture name="taeyai6 instance 10008" x="1737" y="2141" width="579" height="691"/>
	<SubTexture name="taeyai6 instance 10009" x="2316" y="2141" width="579" height="691"/>
	<SubTexture name="taeyai6 instance 10010" x="2895" y="2141" width="579" height="691"/>
	<SubTexture name="taeyai6 instance 10011" x="3474" y="2141" width="579" height="691"/>
	<SubTexture name="taeyai8 instance 10000" x="4053" y="2141" width="512" height="735"/>
	<SubTexture name="taeyai8 instance 10001" x="4565" y="2141" width="512" height="735"/>
	<SubTexture name="taeyai8 instance 10002" x="5077" y="2141" width="512" height="735"/>
	<SubTexture name="taeyai8 instance 10003" x="5589" y="2141" width="512" height="735"/>
	<SubTexture name="taeyai8 instance 10004" x="6101" y="2141" width="512" height="735"/>
	<SubTexture name="taeyai8 instance 10005" x="6613" y="2141" width="512" height="735"/>
	<SubTexture name="taeyai8 instance 10006" x="7125" y="2141" width="512" height="735"/>
	<SubTexture name="taeyai8 instance 10007" x="7637" y="2141" width="512" height="735"/>
	<SubTexture name="taeyai8 instance 10008" x="0" y="2876" width="512" height="735"/>
	<SubTexture name="taeyai8 instance 10009" x="512" y="2876" width="512" height="735"/>
	<SubTexture name="taeyai8 instance 10010" x="1024" y="2876" width="512" height="735"/>
	<SubTexture name="taeyai8 instance 10011" x="1536" y="2876" width="512" height="735"/>
</TextureAtlas>
