{"events":[{"params":[1],"name":"Camera Movement","time":10971.4285714286},{"params":[0],"name":"Camera Movement","time":16457.1428571429},{"params":[1],"name":"Camera Movement","time":21942.8571428571},{"params":[0],"name":"Camera Movement","time":27428.5714285714},{"params":[1],"name":"Camera Movement","time":30171.4285714286},{"params":[0],"name":"Camera Movement","time":32914.2857142857},{"params":[1],"name":"Camera Movement","time":35657.1428571429},{"params":[0],"name":"Camera Movement","time":38400},{"params":[1],"name":"Camera Movement","time":41142.8571428572},{"params":[0],"name":"Camera Movement","time":43885.7142857143},{"params":[1],"name":"Camera Movement","time":46628.5714285714},{"params":[0],"name":"Camera Movement","time":49371.4285714286},{"params":[1],"name":"Camera Movement","time":54857.1428571429},{"params":[0],"name":"Camera Movement","time":60342.8571428572},{"params":[1],"name":"Camera Movement","time":65828.5714285714},{"params":[0],"name":"Camera Movement","time":71314.2857142857},{"params":[1],"name":"Camera Movement","time":74057.1428571428},{"params":[0],"name":"Camera Movement","time":76800},{"params":[1],"name":"Camera Movement","time":79542.8571428571},{"params":[0],"name":"Camera Movement","time":82285.7142857142},{"params":[1],"name":"Camera Movement","time":85028.5714285714},{"params":[0],"name":"Camera Movement","time":87771.4285714285},{"params":[1],"name":"Camera Movement","time":90514.2857142857},{"params":[0],"name":"Camera Movement","time":93257.1428571428},{"params":[1],"name":"Camera Movement","time":98742.857142857},{"params":[0],"name":"Camera Movement","time":104228.571428571},{"params":[1],"name":"Camera Movement","time":109714.285714286},{"params":[0],"name":"Camera Movement","time":115200},{"params":[1],"name":"Camera Movement","time":120685.714285714},{"params":[0],"name":"Camera Movement","time":126171.428571428},{"params":[1],"name":"Camera Movement","time":131657.142857143},{"params":[0],"name":"Camera Movement","time":137142.857142857},{"params":[1],"name":"Camera Movement","time":139885.714285714},{"params":[0],"name":"Camera Movement","time":142628.571428571},{"params":[1],"name":"Camera Movement","time":145371.428571428},{"params":[0],"name":"Camera Movement","time":148114.285714286},{"params":[1],"name":"Camera Movement","time":150857.142857143},{"params":[0],"name":"Camera Movement","time":153600},{"params":[1],"name":"Camera Movement","time":156342.857142857},{"params":[0],"name":"Camera Movement","time":159085.714285714},{"params":[1],"name":"Camera Movement","time":161828.571428571}],"scrollSpeed":3.1,"strumLines":[{"visible":true,"notes":[{"id":0,"sLen":0,"time":5485.71428571429,"type":0},{"id":0,"sLen":0,"time":5571.42857142857,"type":0},{"id":1,"sLen":0,"time":5657.14285714286,"type":0},{"id":3,"sLen":0,"time":5828.57142857143,"type":0},{"id":1,"sLen":0,"time":6000,"type":0},{"id":2,"sLen":0,"time":6171.42857142857,"type":0},{"id":3,"sLen":0,"time":6171.42857142857,"type":0},{"id":0,"sLen":0,"time":6342.85714285714,"type":0},{"id":3,"sLen":0,"time":6514.28571428571,"type":0},{"id":1,"sLen":0,"time":6685.71428571429,"type":0},{"id":3,"sLen":0,"time":6857.14285714286,"type":0},{"id":3,"sLen":0,"time":6942.85714285714,"type":0},{"id":1,"sLen":0,"time":7028.57142857143,"type":0},{"id":0,"sLen":0,"time":7200,"type":0},{"id":1,"sLen":0,"time":7371.42857142857,"type":0},{"id":2,"sLen":0,"time":7542.85714285714,"type":0},{"id":3,"sLen":0,"time":7542.85714285714,"type":0},{"id":1,"sLen":0,"time":7714.28571428571,"type":0},{"id":3,"sLen":0,"time":7885.71428571429,"type":0},{"id":1,"sLen":0,"time":8057.14285714286,"type":0},{"id":0,"sLen":0,"time":8228.57142857143,"type":0},{"id":0,"sLen":0,"time":8314.28571428571,"type":0},{"id":1,"sLen":0,"time":8400,"type":0},{"id":3,"sLen":0,"time":8571.42857142857,"type":0},{"id":1,"sLen":0,"time":8742.85714285714,"type":0},{"id":2,"sLen":0,"time":8914.28571428571,"type":0},{"id":3,"sLen":0,"time":8914.28571428571,"type":0},{"id":0,"sLen":0,"time":9085.71428571428,"type":0},{"id":3,"sLen":0,"time":9257.14285714286,"type":0},{"id":1,"sLen":0,"time":9428.57142857143,"type":0},{"id":3,"sLen":0,"time":9600,"type":0},{"id":3,"sLen":0,"time":9685.71428571428,"type":0},{"id":1,"sLen":0,"time":9771.42857142857,"type":0},{"id":0,"sLen":0,"time":9942.85714285714,"type":0},{"id":1,"sLen":0,"time":10114.2857142857,"type":0},{"id":2,"sLen":0,"time":10285.7142857143,"type":0},{"id":3,"sLen":0,"time":10285.7142857143,"type":0},{"id":1,"sLen":0,"time":10457.1428571429,"type":0},{"id":3,"sLen":0,"time":10628.5714285714,"type":0},{"id":1,"sLen":0,"time":10800,"type":0},{"id":2,"sLen":0,"time":16457.1428571429,"type":0},{"id":2,"sLen":0,"time":16542.8571428571,"type":0},{"id":1,"sLen":0,"time":16628.5714285714,"type":0},{"id":3,"sLen":0,"time":16800,"type":0},{"id":1,"sLen":0,"time":16971.4285714286,"type":0},{"id":2,"sLen":0,"time":17142.8571428571,"type":0},{"id":3,"sLen":0,"time":17142.8571428571,"type":0},{"id":2,"sLen":0,"time":17228.5714285714,"type":0},{"id":3,"sLen":0,"time":17228.5714285714,"type":0},{"id":0,"sLen":0,"time":17314.2857142857,"type":0},{"id":1,"sLen":0,"time":17485.7142857143,"type":0},{"id":0,"sLen":0,"time":17657.1428571429,"type":0},{"id":3,"sLen":0,"time":17828.5714285714,"type":0},{"id":3,"sLen":0,"time":17914.2857142857,"type":0},{"id":0,"sLen":0,"time":18000,"type":0},{"id":1,"sLen":0,"time":18171.4285714286,"type":0},{"id":3,"sLen":0,"time":18342.8571428571,"type":0},{"id":0,"sLen":0,"time":18514.2857142857,"type":0},{"id":2,"sLen":0,"time":18514.2857142857,"type":0},{"id":0,"sLen":0,"time":18600,"type":0},{"id":2,"sLen":0,"time":18600,"type":0},{"id":1,"sLen":0,"time":18685.7142857143,"type":0},{"id":3,"sLen":0,"time":18857.1428571429,"type":0},{"id":1,"sLen":0,"time":19028.5714285714,"type":0},{"id":2,"sLen":0,"time":19200,"type":0},{"id":2,"sLen":0,"time":19285.7142857143,"type":0},{"id":1,"sLen":0,"time":19371.4285714286,"type":0},{"id":3,"sLen":0,"time":19542.8571428571,"type":0},{"id":1,"sLen":0,"time":19714.2857142857,"type":0},{"id":2,"sLen":0,"time":19885.7142857143,"type":0},{"id":3,"sLen":0,"time":19885.7142857143,"type":0},{"id":2,"sLen":0,"time":19971.4285714286,"type":0},{"id":3,"sLen":0,"time":19971.4285714286,"type":0},{"id":0,"sLen":0,"time":20057.1428571429,"type":0},{"id":1,"sLen":0,"time":20228.5714285714,"type":0},{"id":0,"sLen":0,"time":20400,"type":0},{"id":3,"sLen":0,"time":20571.4285714286,"type":0},{"id":3,"sLen":0,"time":20657.1428571429,"type":0},{"id":0,"sLen":0,"time":20742.8571428571,"type":0},{"id":1,"sLen":0,"time":20914.2857142857,"type":0},{"id":3,"sLen":0,"time":21085.7142857143,"type":0},{"id":0,"sLen":0,"time":21257.1428571429,"type":0},{"id":2,"sLen":0,"time":21257.1428571429,"type":0},{"id":0,"sLen":0,"time":21342.8571428571,"type":0},{"id":2,"sLen":0,"time":21342.8571428571,"type":0},{"id":1,"sLen":0,"time":21428.5714285714,"type":0},{"id":3,"sLen":0,"time":21600,"type":0},{"id":1,"sLen":0,"time":21771.4285714286,"type":0},{"id":3,"sLen":0,"time":26057.1428571429,"type":0},{"id":0,"sLen":0,"time":26400,"type":0},{"id":1,"sLen":0,"time":26571.4285714286,"type":0},{"id":0,"sLen":0,"time":26742.8571428571,"type":0},{"id":2,"sLen":0,"time":26914.2857142857,"type":0},{"id":3,"sLen":0,"time":27085.7142857143,"type":0},{"id":1,"sLen":0,"time":27257.1428571429,"type":0},{"id":3,"sLen":257.142857142862,"time":27428.5714285714,"type":0},{"id":1,"sLen":257.142857142855,"time":27771.4285714286,"type":0},{"id":2,"sLen":0,"time":28114.2857142857,"type":0},{"id":1,"sLen":257.142857142855,"time":28285.7142857143,"type":0},{"id":0,"sLen":257.142857142862,"time":28628.5714285714,"type":0},{"id":3,"sLen":257.142857142855,"time":28971.4285714286,"type":0},{"id":1,"sLen":0,"time":29314.2857142857,"type":0},{"id":2,"sLen":0,"time":29485.7142857143,"type":0},{"id":3,"sLen":0,"time":29485.7142857143,"type":0},{"id":0,"sLen":0,"time":29657.1428571429,"type":0},{"id":1,"sLen":257.142857142862,"time":29828.5714285714,"type":0},{"id":2,"sLen":257.142857142855,"time":32914.2857142857,"type":0},{"id":1,"sLen":257.142857142855,"time":33257.1428571429,"type":0},{"id":0,"sLen":85.7142857142826,"time":33600,"type":0},{"id":1,"sLen":85.7142857142826,"time":33771.4285714286,"type":0},{"id":3,"sLen":0,"time":33942.8571428571,"type":0},{"id":2,"sLen":257.142857142855,"time":34114.2857142857,"type":0},{"id":3,"sLen":85.7142857142826,"time":34457.1428571429,"type":0},{"id":1,"sLen":257.142857142855,"time":34628.5714285714,"type":0},{"id":0,"sLen":257.142857142855,"time":34971.4285714286,"type":0},{"id":3,"sLen":257.142857142855,"time":35314.2857142857,"type":0},{"id":0,"sLen":257.142857142855,"time":38400,"type":0},{"id":3,"sLen":257.142857142855,"time":38742.8571428572,"type":0},{"id":0,"sLen":257.142857142855,"time":39085.7142857143,"type":0},{"id":2,"sLen":257.142857142855,"time":39428.5714285714,"type":0},{"id":0,"sLen":257.142857142855,"time":39771.4285714286,"type":0},{"id":3,"sLen":257.142857142855,"time":40114.2857142857,"type":0},{"id":0,"sLen":85.7142857142826,"time":40457.1428571429,"type":0},{"id":3,"sLen":0,"time":40628.5714285714,"type":0},{"id":1,"sLen":257.142857142855,"time":40800,"type":0},{"id":0,"sLen":257.142857142862,"time":43885.7142857143,"type":0},{"id":1,"sLen":0,"time":44228.5714285714,"type":0},{"id":3,"sLen":0,"time":44400,"type":0},{"id":2,"sLen":85.7142857142899,"time":44571.4285714286,"type":0},{"id":1,"sLen":0,"time":44742.8571428571,"type":0},{"id":0,"sLen":0,"time":44914.2857142857,"type":0},{"id":1,"sLen":0,"time":45085.7142857143,"type":0},{"id":2,"sLen":0,"time":45257.1428571429,"type":0},{"id":0,"sLen":0,"time":45428.5714285714,"type":0},{"id":2,"sLen":257.142857142855,"time":45600,"type":0},{"id":3,"sLen":600,"time":45942.8571428572,"type":0},{"id":2,"sLen":428.571428571428,"time":46200,"type":0},{"id":1,"sLen":257.142857142862,"time":46371.4285714286,"type":0},{"id":0,"sLen":257.142857142855,"time":46457.1428571429,"type":0},{"id":0,"sLen":0,"time":49371.4285714286,"type":0},{"id":2,"sLen":0,"time":49542.8571428572,"type":0},{"id":3,"sLen":0,"time":49542.8571428572,"type":0},{"id":0,"sLen":0,"time":49714.2857142857,"type":0},{"id":1,"sLen":0,"time":49885.7142857143,"type":0},{"id":2,"sLen":0,"time":49885.7142857143,"type":0},{"id":3,"sLen":0,"time":50057.1428571429,"type":0},{"id":0,"sLen":0,"time":50228.5714285714,"type":0},{"id":1,"sLen":0,"time":50228.5714285714,"type":0},{"id":3,"sLen":0,"time":50400,"type":0},{"id":1,"sLen":0,"time":50571.4285714286,"type":0},{"id":2,"sLen":0,"time":50571.4285714286,"type":0},{"id":0,"sLen":0,"time":50742.8571428572,"type":0},{"id":1,"sLen":0,"time":50914.2857142857,"type":0},{"id":2,"sLen":0,"time":50914.2857142857,"type":0},{"id":3,"sLen":0,"time":51085.7142857143,"type":0},{"id":1,"sLen":0,"time":51257.1428571429,"type":0},{"id":2,"sLen":0,"time":51257.1428571429,"type":0},{"id":3,"sLen":0,"time":51428.5714285714,"type":0},{"id":0,"sLen":0,"time":51600,"type":0},{"id":2,"sLen":0,"time":51600,"type":0},{"id":1,"sLen":0,"time":51771.4285714286,"type":0},{"id":2,"sLen":0,"time":51942.8571428572,"type":0},{"id":3,"sLen":0,"time":51942.8571428572,"type":0},{"id":0,"sLen":0,"time":52114.2857142857,"type":0},{"id":1,"sLen":0,"time":52285.7142857143,"type":0},{"id":2,"sLen":0,"time":52285.7142857143,"type":0},{"id":3,"sLen":0,"time":52457.1428571429,"type":0},{"id":1,"sLen":0,"time":52628.5714285714,"type":0},{"id":2,"sLen":0,"time":52628.5714285714,"type":0},{"id":0,"sLen":0,"time":52800,"type":0},{"id":1,"sLen":0,"time":52971.4285714286,"type":0},{"id":2,"sLen":0,"time":52971.4285714286,"type":0},{"id":3,"sLen":0,"time":53142.8571428572,"type":0},{"id":1,"sLen":0,"time":53314.2857142857,"type":0},{"id":2,"sLen":0,"time":53314.2857142857,"type":0},{"id":3,"sLen":0,"time":53485.7142857143,"type":0},{"id":0,"sLen":0,"time":53657.1428571429,"type":0},{"id":1,"sLen":0,"time":53828.5714285714,"type":0},{"id":2,"sLen":0,"time":54000,"type":0},{"id":3,"sLen":257.142857142862,"time":54171.4285714286,"type":0},{"id":1,"sLen":257.142857142855,"time":54514.2857142857,"type":0},{"id":2,"sLen":0,"time":58971.4285714286,"type":0},{"id":2,"sLen":0,"time":59228.5714285714,"type":0},{"id":0,"sLen":0,"time":59485.7142857143,"type":0},{"id":2,"sLen":0,"time":59657.1428571429,"type":0},{"id":3,"sLen":0,"time":60000,"type":0},{"id":2,"sLen":257.142857142848,"time":60342.8571428572,"type":0},{"id":0,"sLen":0,"time":60685.7142857143,"type":0},{"id":1,"sLen":0,"time":60857.1428571429,"type":0},{"id":3,"sLen":257.142857142855,"time":61028.5714285714,"type":0},{"id":0,"sLen":257.142857142848,"time":61371.4285714286,"type":0},{"id":2,"sLen":257.142857142855,"time":61714.2857142857,"type":0},{"id":1,"sLen":0,"time":62057.1428571429,"type":0},{"id":0,"sLen":257.142857142862,"time":62228.5714285715,"type":0},{"id":1,"sLen":0,"time":62571.4285714286,"type":0},{"id":3,"sLen":257.142857142848,"time":62742.8571428572,"type":0},{"id":2,"sLen":171.428571428572,"time":63085.7142857143,"type":0},{"id":0,"sLen":171.428571428572,"time":63342.8571428572,"type":0},{"id":2,"sLen":171.428571428587,"time":63600,"type":0},{"id":3,"sLen":171.428571428572,"time":63857.1428571429,"type":0},{"id":0,"sLen":0,"time":64114.2857142857,"type":0},{"id":1,"sLen":0,"time":64285.7142857143,"type":0},{"id":2,"sLen":600,"time":64457.1428571429,"type":0},{"id":3,"sLen":257.142857142862,"time":64457.1428571429,"type":1},{"id":0,"sLen":257.142857142862,"time":64800,"type":1},{"id":1,"sLen":0,"time":64800,"type":1},{"id":1,"sLen":257.142857142848,"time":65142.8571428572,"type":1},{"id":3,"sLen":600,"time":65142.8571428572,"type":0},{"id":0,"sLen":0,"time":65485.7142857143,"type":1},{"id":2,"sLen":257.142857142862,"time":65485.7142857143,"type":1},{"id":2,"sLen":0,"time":68571.4285714286,"type":0},{"id":0,"sLen":0,"time":68828.5714285714,"type":0},{"id":2,"sLen":0,"time":69085.7142857143,"type":0},{"id":3,"sLen":0,"time":69342.8571428571,"type":0},{"id":0,"sLen":0,"time":69600,"type":0},{"id":1,"sLen":0,"time":69771.4285714286,"type":0},{"id":2,"sLen":0,"time":69942.8571428571,"type":0},{"id":0,"sLen":0,"time":70285.7142857143,"type":0},{"id":1,"sLen":0,"time":70457.1428571429,"type":0},{"id":1,"sLen":0,"time":70714.2857142857,"type":0},{"id":3,"sLen":0,"time":70971.4285714286,"type":0},{"id":0,"sLen":0,"time":71314.2857142857,"type":0},{"id":0,"sLen":0,"time":71571.4285714286,"type":0},{"id":0,"sLen":0,"time":71828.5714285714,"type":0},{"id":0,"sLen":0,"time":72085.7142857143,"type":0},{"id":2,"sLen":0,"time":72342.8571428571,"type":0},{"id":3,"sLen":0,"time":72342.8571428571,"type":0},{"id":1,"sLen":0,"time":72514.2857142857,"type":0},{"id":2,"sLen":0,"time":72514.2857142857,"type":0},{"id":3,"sLen":0,"time":72685.7142857143,"type":0},{"id":3,"sLen":0,"time":72942.8571428571,"type":0},{"id":3,"sLen":0,"time":73200,"type":0},{"id":3,"sLen":0,"time":73457.1428571428,"type":0},{"id":0,"sLen":0,"time":73714.2857142857,"type":0},{"id":1,"sLen":0,"time":73714.2857142857,"type":0},{"id":1,"sLen":0,"time":73885.7142857143,"type":0},{"id":2,"sLen":0,"time":73885.7142857143,"type":0},{"id":2,"sLen":0,"time":76114.2857142857,"type":0},{"id":0,"sLen":0,"time":76285.7142857143,"type":0},{"id":1,"sLen":0,"time":76457.1428571429,"type":0},{"id":3,"sLen":0,"time":76628.5714285714,"type":0},{"id":0,"sLen":0,"time":76800,"type":0},{"id":1,"sLen":0,"time":76971.4285714285,"type":0},{"id":3,"sLen":0,"time":77142.8571428571,"type":0},{"id":1,"sLen":0,"time":77314.2857142857,"type":0},{"id":2,"sLen":0,"time":77485.7142857143,"type":0},{"id":3,"sLen":0,"time":77485.7142857143,"type":0},{"id":0,"sLen":0,"time":77657.1428571428,"type":0},{"id":1,"sLen":0,"time":77828.5714285714,"type":0},{"id":2,"sLen":0,"time":77828.5714285714,"type":0},{"id":3,"sLen":0,"time":78000,"type":0},{"id":0,"sLen":0,"time":78171.4285714285,"type":0},{"id":1,"sLen":0,"time":78342.8571428571,"type":0},{"id":3,"sLen":0,"time":78514.2857142857,"type":0},{"id":1,"sLen":0,"time":78685.7142857142,"type":0},{"id":0,"sLen":0,"time":78857.1428571428,"type":0},{"id":2,"sLen":0,"time":78857.1428571428,"type":0},{"id":3,"sLen":0,"time":78857.1428571428,"type":0},{"id":3,"sLen":0,"time":79028.5714285714,"type":0},{"id":0,"sLen":0,"time":79200,"type":0},{"id":1,"sLen":0,"time":79200,"type":0},{"id":2,"sLen":0,"time":79200,"type":0},{"id":2,"sLen":0,"time":79371.4285714285,"type":0},{"id":3,"sLen":0,"time":81600,"type":0},{"id":0,"sLen":0,"time":81771.4285714286,"type":0},{"id":3,"sLen":0,"time":81942.8571428571,"type":0},{"id":3,"sLen":0,"time":82114.2857142857,"type":0},{"id":0,"sLen":257.142857142855,"time":82285.7142857142,"type":0},{"id":1,"sLen":171.428571428565,"time":82285.7142857142,"type":1},{"id":3,"sLen":0,"time":82628.5714285714,"type":0},{"id":2,"sLen":0,"time":82799.9999999999,"type":0},{"id":0,"sLen":171.428571428565,"time":82971.4285714285,"type":1},{"id":1,"sLen":257.142857142855,"time":82971.4285714285,"type":0},{"id":0,"sLen":0,"time":83314.2857142857,"type":0},{"id":1,"sLen":0,"time":83485.7142857142,"type":0},{"id":2,"sLen":171.428571428565,"time":83657.1428571428,"type":1},{"id":3,"sLen":257.142857142855,"time":83657.1428571428,"type":0},{"id":0,"sLen":0,"time":83999.9999999999,"type":0},{"id":1,"sLen":0,"time":84171.4285714285,"type":0},{"id":2,"sLen":257.142857142855,"time":84342.8571428571,"type":0},{"id":3,"sLen":171.428571428565,"time":84342.8571428571,"type":1},{"id":3,"sLen":0,"time":84685.7142857142,"type":0},{"id":2,"sLen":0,"time":84857.1428571428,"type":0},{"id":2,"sLen":0,"time":87085.7142857143,"type":0},{"id":0,"sLen":0,"time":87257.1428571429,"type":0},{"id":1,"sLen":0,"time":87428.5714285714,"type":0},{"id":3,"sLen":0,"time":87600,"type":0},{"id":0,"sLen":0,"time":87771.4285714285,"type":0},{"id":1,"sLen":0,"time":87942.8571428571,"type":0},{"id":3,"sLen":0,"time":88114.2857142856,"type":0},{"id":1,"sLen":0,"time":88285.7142857142,"type":0},{"id":0,"sLen":0,"time":88457.1428571428,"type":0},{"id":2,"sLen":0,"time":88457.1428571428,"type":0},{"id":3,"sLen":0,"time":88457.1428571428,"type":0},{"id":2,"sLen":0,"time":88628.5714285713,"type":0},{"id":0,"sLen":0,"time":88799.9999999999,"type":0},{"id":1,"sLen":0,"time":88799.9999999999,"type":0},{"id":2,"sLen":0,"time":88799.9999999999,"type":0},{"id":3,"sLen":0,"time":88971.4285714285,"type":0},{"id":0,"sLen":0,"time":89142.8571428571,"type":0},{"id":1,"sLen":0,"time":89314.2857142856,"type":0},{"id":3,"sLen":0,"time":89485.7142857142,"type":0},{"id":1,"sLen":0,"time":89657.1428571428,"type":0},{"id":0,"sLen":0,"time":89828.5714285713,"type":0},{"id":2,"sLen":0,"time":89828.5714285713,"type":0},{"id":3,"sLen":0,"time":89828.5714285713,"type":0},{"id":3,"sLen":0,"time":89999.9999999999,"type":0},{"id":0,"sLen":0,"time":90171.4285714285,"type":0},{"id":1,"sLen":0,"time":90171.4285714285,"type":0},{"id":2,"sLen":0,"time":90171.4285714285,"type":0},{"id":3,"sLen":0,"time":90342.8571428571,"type":0},{"id":2,"sLen":0,"time":91885.7142857143,"type":0},{"id":2,"sLen":0,"time":92057.1428571429,"type":0},{"id":0,"sLen":0,"time":92228.5714285714,"type":0},{"id":1,"sLen":0,"time":92400,"type":0},{"id":0,"sLen":0,"time":92571.4285714285,"type":0},{"id":2,"sLen":0,"time":92571.4285714285,"type":0},{"id":3,"sLen":0,"time":92571.4285714285,"type":0},{"id":3,"sLen":0,"time":92742.8571428571,"type":0},{"id":0,"sLen":0,"time":92914.2857142856,"type":0},{"id":1,"sLen":0,"time":92914.2857142856,"type":0},{"id":2,"sLen":0,"time":92914.2857142856,"type":0},{"id":3,"sLen":0,"time":93085.7142857142,"type":0},{"id":0,"sLen":0,"time":93257.1428571429,"type":0},{"id":2,"sLen":0,"time":93428.5714285714,"type":0},{"id":3,"sLen":0,"time":93428.5714285714,"type":0},{"id":0,"sLen":0,"time":93600,"type":0},{"id":1,"sLen":0,"time":93771.4285714286,"type":0},{"id":2,"sLen":0,"time":93771.4285714286,"type":0},{"id":3,"sLen":0,"time":93942.8571428572,"type":0},{"id":0,"sLen":0,"time":94114.2857142857,"type":0},{"id":1,"sLen":0,"time":94114.2857142857,"type":0},{"id":3,"sLen":0,"time":94285.7142857143,"type":0},{"id":1,"sLen":0,"time":94457.1428571429,"type":0},{"id":2,"sLen":0,"time":94457.1428571429,"type":0},{"id":0,"sLen":0,"time":94628.5714285714,"type":0},{"id":1,"sLen":0,"time":94800,"type":0},{"id":2,"sLen":0,"time":94800,"type":0},{"id":3,"sLen":0,"time":94971.4285714286,"type":0},{"id":1,"sLen":0,"time":95142.8571428572,"type":0},{"id":2,"sLen":0,"time":95142.8571428572,"type":0},{"id":3,"sLen":0,"time":95314.2857142857,"type":0},{"id":0,"sLen":0,"time":95485.7142857143,"type":0},{"id":2,"sLen":0,"time":95485.7142857143,"type":0},{"id":1,"sLen":0,"time":95657.1428571429,"type":0},{"id":2,"sLen":0,"time":95828.5714285714,"type":0},{"id":3,"sLen":0,"time":95828.5714285714,"type":0},{"id":0,"sLen":0,"time":96000,"type":0},{"id":1,"sLen":0,"time":96171.4285714286,"type":0},{"id":2,"sLen":0,"time":96171.4285714286,"type":0},{"id":3,"sLen":0,"time":96342.8571428572,"type":0},{"id":1,"sLen":0,"time":96514.2857142857,"type":0},{"id":2,"sLen":0,"time":96514.2857142857,"type":0},{"id":0,"sLen":0,"time":96685.7142857143,"type":0},{"id":1,"sLen":0,"time":96857.1428571429,"type":0},{"id":2,"sLen":0,"time":96857.1428571429,"type":0},{"id":3,"sLen":0,"time":97028.5714285714,"type":0},{"id":1,"sLen":0,"time":97200,"type":0},{"id":2,"sLen":0,"time":97200,"type":0},{"id":3,"sLen":0,"time":97371.4285714286,"type":0},{"id":0,"sLen":0,"time":97542.8571428572,"type":0},{"id":1,"sLen":0,"time":97714.2857142857,"type":0},{"id":2,"sLen":0,"time":97885.7142857143,"type":0},{"id":3,"sLen":257.142857142855,"time":98057.1428571429,"type":0},{"id":1,"sLen":257.142857142855,"time":98400,"type":0},{"id":0,"sLen":0,"time":102857.142857143,"type":0},{"id":0,"sLen":0,"time":103114.285714286,"type":0},{"id":1,"sLen":0,"time":103371.428571429,"type":0},{"id":0,"sLen":0,"time":103542.857142857,"type":0},{"id":3,"sLen":0,"time":103885.714285714,"type":0},{"id":2,"sLen":257.142857142855,"time":104228.571428571,"type":0},{"id":0,"sLen":0,"time":104571.428571429,"type":0},{"id":1,"sLen":0,"time":104742.857142857,"type":0},{"id":3,"sLen":257.142857142855,"time":104914.285714286,"type":0},{"id":0,"sLen":257.142857142855,"time":105257.142857143,"type":0},{"id":2,"sLen":257.142857142884,"time":105600,"type":0},{"id":1,"sLen":0,"time":105942.857142857,"type":0},{"id":0,"sLen":257.142857142855,"time":106114.285714286,"type":0},{"id":1,"sLen":0,"time":106457.142857143,"type":0},{"id":3,"sLen":257.142857142855,"time":106628.571428571,"type":0},{"id":2,"sLen":171.42857142858,"time":106971.428571429,"type":0},{"id":0,"sLen":171.428571428565,"time":107228.571428571,"type":0},{"id":2,"sLen":171.428571428565,"time":107485.714285714,"type":0},{"id":3,"sLen":171.428571428565,"time":107742.857142857,"type":0},{"id":0,"sLen":0,"time":108000,"type":0},{"id":1,"sLen":0,"time":108171.428571429,"type":0},{"id":2,"sLen":600,"time":108342.857142857,"type":0},{"id":3,"sLen":257.142857142855,"time":108342.857142857,"type":1},{"id":0,"sLen":257.14285714287,"time":108685.714285714,"type":1},{"id":1,"sLen":0,"time":108685.714285714,"type":1},{"id":1,"sLen":257.142857142855,"time":109028.571428571,"type":1},{"id":3,"sLen":600,"time":109028.571428571,"type":0},{"id":0,"sLen":0,"time":109371.428571429,"type":1},{"id":2,"sLen":257.14285714287,"time":109371.428571429,"type":1},{"id":2,"sLen":0,"time":112457.142857143,"type":0},{"id":0,"sLen":0,"time":112714.285714286,"type":0},{"id":2,"sLen":0,"time":112971.428571429,"type":0},{"id":3,"sLen":0,"time":113228.571428571,"type":0},{"id":0,"sLen":0,"time":113485.714285714,"type":0},{"id":1,"sLen":0,"time":113657.142857143,"type":0},{"id":2,"sLen":0,"time":113828.571428571,"type":0},{"id":0,"sLen":0,"time":114171.428571429,"type":0},{"id":1,"sLen":0,"time":114171.428571429,"type":0},{"id":2,"sLen":0,"time":114342.857142857,"type":0},{"id":1,"sLen":0,"time":114514.285714286,"type":0},{"id":3,"sLen":0,"time":114514.285714286,"type":0},{"id":0,"sLen":0,"time":114857.142857143,"type":0},{"id":2,"sLen":0,"time":114857.142857143,"type":0},{"id":0,"sLen":0,"time":115200,"type":0},{"id":2,"sLen":0,"time":115371.428571428,"type":0},{"id":0,"sLen":0,"time":115457.142857143,"type":0},{"id":3,"sLen":0,"time":115628.571428571,"type":0},{"id":0,"sLen":0,"time":115714.285714286,"type":0},{"id":2,"sLen":0,"time":115885.714285714,"type":0},{"id":0,"sLen":0,"time":115971.428571428,"type":0},{"id":3,"sLen":0,"time":116142.857142857,"type":0},{"id":0,"sLen":0,"time":116228.571428571,"type":0},{"id":0,"sLen":0,"time":116400,"type":0},{"id":3,"sLen":0,"time":116571.428571428,"type":0},{"id":1,"sLen":0,"time":116742.857142857,"type":0},{"id":3,"sLen":0,"time":116828.571428571,"type":0},{"id":0,"sLen":0,"time":117000,"type":0},{"id":3,"sLen":0,"time":117085.714285714,"type":0},{"id":1,"sLen":0,"time":117257.142857143,"type":0},{"id":3,"sLen":0,"time":117342.857142857,"type":0},{"id":0,"sLen":0,"time":117514.285714286,"type":0},{"id":3,"sLen":0,"time":117600,"type":0},{"id":3,"sLen":0,"time":117771.428571428,"type":0},{"id":1,"sLen":0,"time":117942.857142857,"type":0},{"id":3,"sLen":0,"time":118114.285714286,"type":0},{"id":1,"sLen":0,"time":118200,"type":0},{"id":0,"sLen":0,"time":118371.428571428,"type":0},{"id":1,"sLen":0,"time":118457.142857143,"type":0},{"id":3,"sLen":0,"time":118628.571428571,"type":0},{"id":1,"sLen":0,"time":118714.285714285,"type":0},{"id":0,"sLen":0,"time":118885.714285714,"type":0},{"id":1,"sLen":0,"time":118971.428571428,"type":0},{"id":1,"sLen":0,"time":119142.857142857,"type":0},{"id":2,"sLen":0,"time":119314.285714285,"type":0},{"id":0,"sLen":0,"time":119485.714285714,"type":0},{"id":2,"sLen":0,"time":119571.428571428,"type":0},{"id":3,"sLen":0,"time":119742.857142857,"type":0},{"id":2,"sLen":0,"time":119828.571428571,"type":0},{"id":0,"sLen":0,"time":120000,"type":0},{"id":2,"sLen":0,"time":120085.714285714,"type":0},{"id":3,"sLen":0,"time":120257.142857143,"type":0},{"id":2,"sLen":0,"time":120342.857142857,"type":0},{"id":2,"sLen":0,"time":120514.285714285,"type":0},{"id":0,"sLen":0,"time":126171.428571428,"type":0},{"id":0,"sLen":0,"time":126257.142857143,"type":0},{"id":1,"sLen":0,"time":126342.857142857,"type":0},{"id":3,"sLen":0,"time":126514.285714285,"type":0},{"id":1,"sLen":0,"time":126685.714285714,"type":0},{"id":2,"sLen":0,"time":126857.142857143,"type":0},{"id":3,"sLen":0,"time":126857.142857143,"type":0},{"id":0,"sLen":0,"time":127028.571428571,"type":0},{"id":3,"sLen":0,"time":127200,"type":0},{"id":1,"sLen":0,"time":127371.428571428,"type":0},{"id":3,"sLen":0,"time":127542.857142857,"type":0},{"id":3,"sLen":0,"time":127628.571428571,"type":0},{"id":1,"sLen":0,"time":127714.285714285,"type":0},{"id":0,"sLen":0,"time":127885.714285714,"type":0},{"id":1,"sLen":0,"time":128057.142857143,"type":0},{"id":2,"sLen":0,"time":128228.571428571,"type":0},{"id":3,"sLen":0,"time":128228.571428571,"type":0},{"id":1,"sLen":0,"time":128400,"type":0},{"id":3,"sLen":0,"time":128571.428571428,"type":0},{"id":1,"sLen":0,"time":128742.857142857,"type":0},{"id":0,"sLen":0,"time":128914.285714285,"type":0},{"id":0,"sLen":0,"time":129000,"type":0},{"id":1,"sLen":0,"time":129085.714285714,"type":0},{"id":3,"sLen":0,"time":129257.142857143,"type":0},{"id":1,"sLen":0,"time":129428.571428571,"type":0},{"id":2,"sLen":0,"time":129600,"type":0},{"id":3,"sLen":0,"time":129600,"type":0},{"id":0,"sLen":0,"time":129771.428571428,"type":0},{"id":3,"sLen":0,"time":129942.857142857,"type":0},{"id":1,"sLen":0,"time":130114.285714285,"type":0},{"id":3,"sLen":0,"time":130285.714285714,"type":0},{"id":3,"sLen":0,"time":130371.428571429,"type":0},{"id":1,"sLen":0,"time":130457.142857143,"type":0},{"id":0,"sLen":0,"time":130628.571428571,"type":0},{"id":1,"sLen":0,"time":130800,"type":0},{"id":2,"sLen":0,"time":130971.428571428,"type":0},{"id":3,"sLen":0,"time":130971.428571428,"type":0},{"id":1,"sLen":0,"time":131142.857142857,"type":0},{"id":3,"sLen":0,"time":131314.285714285,"type":0},{"id":1,"sLen":0,"time":131485.714285714,"type":0},{"id":2,"sLen":0,"time":135771.428571429,"type":0},{"id":1,"sLen":0,"time":136114.285714286,"type":0},{"id":0,"sLen":0,"time":136285.714285714,"type":0},{"id":1,"sLen":0,"time":136457.142857143,"type":0},{"id":3,"sLen":0,"time":136628.571428571,"type":0},{"id":2,"sLen":0,"time":136800,"type":0},{"id":0,"sLen":0,"time":137057.142857143,"type":0},{"id":0,"sLen":257.14285714287,"time":137142.857142857,"type":0},{"id":1,"sLen":257.14285714287,"time":137485.714285714,"type":0},{"id":0,"sLen":0,"time":137828.571428571,"type":0},{"id":1,"sLen":257.14285714287,"time":138000,"type":0},{"id":3,"sLen":257.14285714287,"time":138342.857142857,"type":0},{"id":2,"sLen":257.14285714287,"time":138685.714285714,"type":0},{"id":1,"sLen":0,"time":139028.571428571,"type":0},{"id":2,"sLen":0,"time":139200,"type":0},{"id":3,"sLen":0,"time":139371.428571428,"type":0},{"id":1,"sLen":257.14285714287,"time":139542.857142857,"type":0},{"id":2,"sLen":257.14285714287,"time":142628.571428571,"type":0},{"id":3,"sLen":257.14285714287,"time":142971.428571428,"type":0},{"id":0,"sLen":85.7142857142899,"time":143314.285714286,"type":0},{"id":1,"sLen":85.7142857142608,"time":143485.714285714,"type":0},{"id":3,"sLen":0,"time":143657.142857143,"type":0},{"id":2,"sLen":0,"time":143828.571428571,"type":0},{"id":2,"sLen":0,"time":144171.428571428,"type":0},{"id":3,"sLen":257.14285714287,"time":144342.857142857,"type":0},{"id":0,"sLen":257.14285714287,"time":144685.714285714,"type":0},{"id":3,"sLen":257.14285714287,"time":145028.571428571,"type":0},{"id":0,"sLen":257.14285714287,"time":148114.285714286,"type":0},{"id":1,"sLen":257.14285714287,"time":148457.142857143,"type":0},{"id":3,"sLen":257.14285714287,"time":148800,"type":0},{"id":2,"sLen":257.14285714287,"time":149142.857142857,"type":0},{"id":0,"sLen":257.14285714287,"time":149485.714285714,"type":0},{"id":3,"sLen":600,"time":149485.714285714,"type":1},{"id":2,"sLen":257.14285714287,"time":149828.571428571,"type":0},{"id":0,"sLen":85.7142857142899,"time":150171.428571428,"type":0},{"id":1,"sLen":85.7142857142899,"time":150171.428571428,"type":0},{"id":2,"sLen":0,"time":150342.857142857,"type":0},{"id":3,"sLen":257.14285714287,"time":150514.285714286,"type":0},{"id":0,"sLen":257.14285714287,"time":153600,"type":0},{"id":3,"sLen":0,"time":153942.857142857,"type":0},{"id":2,"sLen":0,"time":154114.285714286,"type":0},{"id":1,"sLen":85.7142857142899,"time":154285.714285714,"type":0},{"id":0,"sLen":0,"time":154457.142857143,"type":0},{"id":3,"sLen":0,"time":154628.571428571,"type":0},{"id":1,"sLen":0,"time":154800,"type":0},{"id":2,"sLen":0,"time":154971.428571428,"type":0},{"id":3,"sLen":0,"time":154971.428571428,"type":0},{"id":0,"sLen":0,"time":155142.857142857,"type":0},{"id":1,"sLen":257.14285714287,"time":155314.285714286,"type":0},{"id":2,"sLen":0,"time":155657.142857143,"type":1},{"id":3,"sLen":600,"time":155657.142857143,"type":0}],"position":"dad","type":0,"characters":["hex_night"]},{"visible":true,"notes":[{"id":0,"sLen":0,"time":10971.4285714286,"type":0},{"id":0,"sLen":0,"time":11057.1428571429,"type":0},{"id":1,"sLen":0,"time":11142.8571428571,"type":0},{"id":3,"sLen":0,"time":11314.2857142857,"type":0},{"id":1,"sLen":0,"time":11485.7142857143,"type":0},{"id":2,"sLen":0,"time":11657.1428571429,"type":0},{"id":3,"sLen":0,"time":11657.1428571429,"type":0},{"id":0,"sLen":0,"time":11828.5714285714,"type":0},{"id":3,"sLen":0,"time":12000,"type":0},{"id":1,"sLen":0,"time":12171.4285714286,"type":0},{"id":3,"sLen":0,"time":12342.8571428571,"type":0},{"id":3,"sLen":0,"time":12428.5714285714,"type":0},{"id":1,"sLen":0,"time":12514.2857142857,"type":0},{"id":0,"sLen":0,"time":12685.7142857143,"type":0},{"id":1,"sLen":0,"time":12857.1428571429,"type":0},{"id":2,"sLen":0,"time":13028.5714285714,"type":0},{"id":3,"sLen":0,"time":13028.5714285714,"type":0},{"id":1,"sLen":0,"time":13200,"type":0},{"id":3,"sLen":0,"time":13371.4285714286,"type":0},{"id":1,"sLen":0,"time":13542.8571428571,"type":0},{"id":0,"sLen":0,"time":13714.2857142857,"type":0},{"id":0,"sLen":0,"time":13800,"type":0},{"id":1,"sLen":0,"time":13885.7142857143,"type":0},{"id":3,"sLen":0,"time":14057.1428571429,"type":0},{"id":1,"sLen":0,"time":14228.5714285714,"type":0},{"id":2,"sLen":0,"time":14400,"type":0},{"id":3,"sLen":0,"time":14400,"type":0},{"id":0,"sLen":0,"time":14571.4285714286,"type":0},{"id":3,"sLen":0,"time":14742.8571428571,"type":0},{"id":1,"sLen":0,"time":14914.2857142857,"type":0},{"id":3,"sLen":0,"time":15085.7142857143,"type":0},{"id":3,"sLen":0,"time":15171.4285714286,"type":0},{"id":1,"sLen":0,"time":15257.1428571429,"type":0},{"id":0,"sLen":0,"time":15428.5714285714,"type":0},{"id":1,"sLen":0,"time":15600,"type":0},{"id":2,"sLen":0,"time":15771.4285714286,"type":0},{"id":3,"sLen":0,"time":15771.4285714286,"type":0},{"id":1,"sLen":0,"time":15942.8571428571,"type":0},{"id":3,"sLen":0,"time":16114.2857142857,"type":0},{"id":1,"sLen":0,"time":16285.7142857143,"type":0},{"id":0,"sLen":0,"time":16457.1428571429,"type":0},{"id":1,"sLen":0,"time":16628.5714285714,"type":0},{"id":3,"sLen":0,"time":16800,"type":0},{"id":1,"sLen":0,"time":16971.4285714286,"type":0},{"id":2,"sLen":0,"time":21942.8571428571,"type":0},{"id":2,"sLen":0,"time":22028.5714285714,"type":0},{"id":1,"sLen":0,"time":22114.2857142857,"type":0},{"id":3,"sLen":0,"time":22285.7142857143,"type":0},{"id":1,"sLen":0,"time":22457.1428571429,"type":0},{"id":2,"sLen":0,"time":22628.5714285714,"type":0},{"id":3,"sLen":0,"time":22628.5714285714,"type":0},{"id":2,"sLen":0,"time":22714.2857142857,"type":0},{"id":3,"sLen":0,"time":22714.2857142857,"type":0},{"id":0,"sLen":0,"time":22800,"type":0},{"id":1,"sLen":0,"time":22971.4285714286,"type":0},{"id":0,"sLen":0,"time":23142.8571428571,"type":0},{"id":3,"sLen":0,"time":23314.2857142857,"type":0},{"id":3,"sLen":0,"time":23400,"type":0},{"id":0,"sLen":0,"time":23485.7142857143,"type":0},{"id":1,"sLen":0,"time":23657.1428571428,"type":0},{"id":3,"sLen":0,"time":23828.5714285714,"type":0},{"id":0,"sLen":0,"time":24000,"type":0},{"id":2,"sLen":0,"time":24000,"type":0},{"id":0,"sLen":0,"time":24085.7142857143,"type":0},{"id":2,"sLen":0,"time":24085.7142857143,"type":0},{"id":1,"sLen":0,"time":24171.4285714286,"type":0},{"id":3,"sLen":0,"time":24342.8571428571,"type":0},{"id":1,"sLen":0,"time":24514.2857142857,"type":0},{"id":2,"sLen":0,"time":24685.7142857143,"type":0},{"id":2,"sLen":0,"time":24771.4285714286,"type":0},{"id":1,"sLen":0,"time":24857.1428571429,"type":0},{"id":3,"sLen":0,"time":25028.5714285714,"type":0},{"id":1,"sLen":0,"time":25200,"type":0},{"id":2,"sLen":0,"time":25371.4285714286,"type":0},{"id":3,"sLen":0,"time":25371.4285714286,"type":0},{"id":2,"sLen":0,"time":25457.1428571429,"type":0},{"id":3,"sLen":0,"time":25457.1428571429,"type":0},{"id":0,"sLen":0,"time":25542.8571428571,"type":0},{"id":1,"sLen":0,"time":25714.2857142857,"type":0},{"id":0,"sLen":0,"time":25885.7142857143,"type":0},{"id":3,"sLen":0,"time":26057.1428571428,"type":0},{"id":3,"sLen":0,"time":26142.8571428571,"type":0},{"id":0,"sLen":0,"time":26228.5714285714,"type":0},{"id":1,"sLen":0,"time":26400,"type":0},{"id":3,"sLen":0,"time":26571.4285714286,"type":0},{"id":0,"sLen":0,"time":26742.8571428571,"type":0},{"id":2,"sLen":0,"time":26742.8571428571,"type":0},{"id":0,"sLen":0,"time":26828.5714285714,"type":0},{"id":2,"sLen":0,"time":26828.5714285714,"type":0},{"id":1,"sLen":0,"time":26914.2857142857,"type":0},{"id":3,"sLen":0,"time":27085.7142857143,"type":0},{"id":1,"sLen":0,"time":27257.1428571428,"type":0},{"id":3,"sLen":0,"time":30171.4285714286,"type":0},{"id":1,"sLen":0,"time":30514.2857142857,"type":0},{"id":2,"sLen":0,"time":30857.1428571429,"type":0},{"id":1,"sLen":0,"time":31028.5714285714,"type":0},{"id":0,"sLen":0,"time":31371.4285714286,"type":0},{"id":3,"sLen":0,"time":31714.2857142857,"type":0},{"id":1,"sLen":0,"time":32057.1428571429,"type":0},{"id":2,"sLen":0,"time":32228.5714285714,"type":0},{"id":3,"sLen":0,"time":32228.5714285714,"type":0},{"id":0,"sLen":0,"time":32400,"type":0},{"id":1,"sLen":0,"time":32571.4285714286,"type":0},{"id":2,"sLen":0,"time":35657.1428571429,"type":0},{"id":1,"sLen":0,"time":36000,"type":0},{"id":0,"sLen":0,"time":36342.8571428571,"type":0},{"id":2,"sLen":0,"time":36514.2857142857,"type":0},{"id":3,"sLen":0,"time":36685.7142857143,"type":0},{"id":2,"sLen":0,"time":36857.1428571429,"type":0},{"id":3,"sLen":0,"time":37200,"type":0},{"id":1,"sLen":0,"time":37371.4285714286,"type":0},{"id":0,"sLen":0,"time":37714.2857142857,"type":0},{"id":3,"sLen":0,"time":38057.1428571429,"type":0},{"id":0,"sLen":0,"time":41142.8571428572,"type":0},{"id":3,"sLen":0,"time":41485.7142857143,"type":0},{"id":0,"sLen":0,"time":41828.5714285714,"type":0},{"id":2,"sLen":0,"time":42171.4285714286,"type":0},{"id":0,"sLen":257.142857142855,"time":42514.2857142857,"type":0},{"id":3,"sLen":0,"time":42857.1428571429,"type":0},{"id":0,"sLen":0,"time":43200,"type":0},{"id":3,"sLen":0,"time":43371.4285714286,"type":0},{"id":1,"sLen":0,"time":43542.8571428572,"type":0},{"id":0,"sLen":257.142857142855,"time":46628.5714285714,"type":0},{"id":1,"sLen":0,"time":46971.4285714286,"type":0},{"id":3,"sLen":0,"time":47142.8571428572,"type":0},{"id":2,"sLen":0,"time":47314.2857142857,"type":0},{"id":1,"sLen":0,"time":47485.7142857143,"type":0},{"id":0,"sLen":0,"time":47657.1428571429,"type":0},{"id":1,"sLen":0,"time":47828.5714285714,"type":0},{"id":2,"sLen":0,"time":48000,"type":0},{"id":0,"sLen":0,"time":48171.4285714286,"type":0},{"id":2,"sLen":0,"time":48342.8571428572,"type":0},{"id":3,"sLen":600,"time":48685.7142857143,"type":0},{"id":2,"sLen":428.571428571428,"time":48857.1428571429,"type":0},{"id":0,"sLen":0,"time":54857.1428571429,"type":0},{"id":2,"sLen":0,"time":55028.5714285714,"type":0},{"id":3,"sLen":0,"time":55028.5714285714,"type":0},{"id":0,"sLen":0,"time":55200,"type":0},{"id":1,"sLen":0,"time":55371.4285714286,"type":0},{"id":2,"sLen":0,"time":55371.4285714286,"type":0},{"id":3,"sLen":0,"time":55542.8571428572,"type":0},{"id":0,"sLen":0,"time":55714.2857142857,"type":0},{"id":1,"sLen":0,"time":55714.2857142857,"type":0},{"id":3,"sLen":0,"time":55885.7142857143,"type":0},{"id":1,"sLen":0,"time":56057.1428571429,"type":0},{"id":2,"sLen":0,"time":56057.1428571429,"type":0},{"id":0,"sLen":0,"time":56228.5714285714,"type":0},{"id":1,"sLen":0,"time":56400,"type":0},{"id":2,"sLen":0,"time":56400,"type":0},{"id":3,"sLen":0,"time":56571.4285714286,"type":0},{"id":1,"sLen":0,"time":56742.8571428572,"type":0},{"id":2,"sLen":0,"time":56742.8571428572,"type":0},{"id":3,"sLen":0,"time":56914.2857142857,"type":0},{"id":0,"sLen":0,"time":57085.7142857143,"type":0},{"id":2,"sLen":0,"time":57085.7142857143,"type":0},{"id":1,"sLen":0,"time":57257.1428571429,"type":0},{"id":2,"sLen":0,"time":57428.5714285714,"type":0},{"id":3,"sLen":0,"time":57428.5714285714,"type":0},{"id":0,"sLen":0,"time":57600,"type":0},{"id":1,"sLen":0,"time":57771.4285714286,"type":0},{"id":2,"sLen":0,"time":57771.4285714286,"type":0},{"id":3,"sLen":0,"time":57942.8571428572,"type":0},{"id":1,"sLen":0,"time":58114.2857142857,"type":0},{"id":2,"sLen":0,"time":58114.2857142857,"type":0},{"id":0,"sLen":0,"time":58285.7142857143,"type":0},{"id":1,"sLen":0,"time":58457.1428571429,"type":0},{"id":2,"sLen":0,"time":58457.1428571429,"type":0},{"id":3,"sLen":0,"time":58628.5714285714,"type":0},{"id":1,"sLen":0,"time":58800,"type":0},{"id":2,"sLen":0,"time":58800,"type":0},{"id":3,"sLen":0,"time":58971.4285714286,"type":0},{"id":0,"sLen":0,"time":59142.8571428572,"type":0},{"id":1,"sLen":0,"time":59314.2857142857,"type":0},{"id":2,"sLen":0,"time":59485.7142857143,"type":0},{"id":3,"sLen":0,"time":59657.1428571429,"type":0},{"id":0,"sLen":0,"time":60000,"type":0},{"id":2,"sLen":0,"time":64457.1428571429,"type":0},{"id":2,"sLen":0,"time":64800,"type":0},{"id":0,"sLen":0,"time":64971.4285714286,"type":0},{"id":1,"sLen":0,"time":65142.8571428571,"type":0},{"id":3,"sLen":0,"time":65485.7142857143,"type":0},{"id":2,"sLen":257.142857142855,"time":65828.5714285714,"type":0},{"id":0,"sLen":0,"time":66171.4285714286,"type":0},{"id":1,"sLen":0,"time":66342.8571428572,"type":0},{"id":3,"sLen":257.142857142855,"time":66514.2857142857,"type":0},{"id":0,"sLen":257.142857142855,"time":66857.1428571429,"type":0},{"id":2,"sLen":257.142857142855,"time":67200,"type":0},{"id":1,"sLen":0,"time":67542.8571428571,"type":0},{"id":0,"sLen":257.142857142855,"time":67714.2857142857,"type":0},{"id":1,"sLen":0,"time":68057.1428571429,"type":0},{"id":3,"sLen":257.142857142855,"time":68228.5714285714,"type":0},{"id":2,"sLen":0,"time":68571.4285714286,"type":0},{"id":0,"sLen":0,"time":68828.5714285714,"type":0},{"id":2,"sLen":0,"time":69085.7142857143,"type":0},{"id":3,"sLen":0,"time":69342.8571428571,"type":0},{"id":0,"sLen":0,"time":69600,"type":0},{"id":1,"sLen":0,"time":69771.4285714286,"type":0},{"id":2,"sLen":600,"time":69942.8571428572,"type":0},{"id":3,"sLen":257.142857142855,"time":69942.8571428572,"type":1},{"id":0,"sLen":257.142857142855,"time":70285.7142857143,"type":1},{"id":1,"sLen":0,"time":70285.7142857143,"type":1},{"id":1,"sLen":257.142857142855,"time":70628.5714285714,"type":1},{"id":3,"sLen":600,"time":70628.5714285714,"type":0},{"id":0,"sLen":0,"time":70971.4285714286,"type":1},{"id":2,"sLen":257.142857142855,"time":70971.4285714286,"type":1},{"id":0,"sLen":0,"time":74057.1428571429,"type":0},{"id":0,"sLen":0,"time":74314.2857142857,"type":0},{"id":0,"sLen":0,"time":74571.4285714286,"type":0},{"id":0,"sLen":0,"time":74828.5714285714,"type":0},{"id":2,"sLen":0,"time":75085.7142857143,"type":0},{"id":3,"sLen":0,"time":75085.7142857143,"type":0},{"id":1,"sLen":0,"time":75257.1428571429,"type":0},{"id":2,"sLen":0,"time":75257.1428571429,"type":0},{"id":3,"sLen":0,"time":75428.5714285714,"type":0},{"id":3,"sLen":0,"time":75685.7142857143,"type":0},{"id":3,"sLen":0,"time":75942.8571428571,"type":0},{"id":3,"sLen":0,"time":76200,"type":0},{"id":0,"sLen":0,"time":76457.1428571429,"type":0},{"id":1,"sLen":0,"time":76457.1428571429,"type":0},{"id":1,"sLen":0,"time":76628.5714285714,"type":0},{"id":2,"sLen":0,"time":76628.5714285714,"type":0},{"id":0,"sLen":0,"time":79542.8571428571,"type":0},{"id":1,"sLen":0,"time":79714.2857142857,"type":0},{"id":3,"sLen":0,"time":79885.7142857143,"type":0},{"id":1,"sLen":0,"time":80057.1428571428,"type":0},{"id":2,"sLen":0,"time":80228.5714285714,"type":0},{"id":3,"sLen":0,"time":80228.5714285714,"type":0},{"id":0,"sLen":0,"time":80400,"type":0},{"id":1,"sLen":0,"time":80571.4285714286,"type":0},{"id":2,"sLen":0,"time":80571.4285714286,"type":0},{"id":3,"sLen":0,"time":80742.8571428571,"type":0},{"id":0,"sLen":0,"time":80914.2857142857,"type":0},{"id":1,"sLen":0,"time":81085.7142857142,"type":0},{"id":3,"sLen":0,"time":81257.1428571428,"type":0},{"id":1,"sLen":0,"time":81428.5714285714,"type":0},{"id":0,"sLen":0,"time":81600,"type":0},{"id":2,"sLen":0,"time":81600,"type":0},{"id":3,"sLen":0,"time":81600,"type":0},{"id":3,"sLen":0,"time":81771.4285714285,"type":0},{"id":0,"sLen":0,"time":81942.8571428571,"type":0},{"id":1,"sLen":0,"time":81942.8571428571,"type":0},{"id":2,"sLen":0,"time":81942.8571428571,"type":0},{"id":2,"sLen":0,"time":82114.2857142857,"type":0},{"id":0,"sLen":0,"time":85028.5714285714,"type":0},{"id":1,"sLen":0,"time":85028.5714285714,"type":1},{"id":3,"sLen":0,"time":85371.4285714285,"type":0},{"id":2,"sLen":0,"time":85542.8571428571,"type":0},{"id":0,"sLen":0,"time":85714.2857142857,"type":1},{"id":1,"sLen":0,"time":85714.2857142857,"type":0},{"id":0,"sLen":0,"time":86057.1428571428,"type":0},{"id":1,"sLen":0,"time":86228.5714285714,"type":0},{"id":2,"sLen":0,"time":86399.9999999999,"type":1},{"id":3,"sLen":0,"time":86399.9999999999,"type":0},{"id":0,"sLen":0,"time":86742.8571428571,"type":0},{"id":1,"sLen":0,"time":86914.2857142857,"type":0},{"id":2,"sLen":0,"time":87085.7142857142,"type":0},{"id":3,"sLen":0,"time":87085.7142857142,"type":1},{"id":3,"sLen":0,"time":87428.5714285714,"type":0},{"id":2,"sLen":0,"time":87599.9999999999,"type":0},{"id":0,"sLen":0,"time":90514.2857142856,"type":0},{"id":1,"sLen":0,"time":90685.7142857142,"type":0},{"id":3,"sLen":0,"time":90857.1428571428,"type":0},{"id":1,"sLen":0,"time":91028.5714285713,"type":0},{"id":0,"sLen":0,"time":91199.9999999999,"type":0},{"id":2,"sLen":0,"time":91199.9999999999,"type":0},{"id":3,"sLen":0,"time":91199.9999999999,"type":0},{"id":2,"sLen":0,"time":91371.4285714285,"type":0},{"id":0,"sLen":0,"time":91542.8571428571,"type":0},{"id":1,"sLen":0,"time":91542.8571428571,"type":0},{"id":2,"sLen":0,"time":91542.8571428571,"type":0},{"id":3,"sLen":0,"time":91714.2857142856,"type":0},{"id":0,"sLen":0,"time":91885.7142857142,"type":0},{"id":1,"sLen":0,"time":92057.1428571428,"type":0},{"id":3,"sLen":0,"time":92228.5714285713,"type":0},{"id":1,"sLen":0,"time":92399.9999999999,"type":0},{"id":0,"sLen":0,"time":92571.4285714285,"type":0},{"id":2,"sLen":0,"time":92571.4285714285,"type":0},{"id":3,"sLen":0,"time":92571.4285714285,"type":0},{"id":3,"sLen":0,"time":92742.8571428571,"type":0},{"id":0,"sLen":0,"time":92914.2857142856,"type":0},{"id":1,"sLen":0,"time":92914.2857142856,"type":0},{"id":2,"sLen":0,"time":92914.2857142856,"type":0},{"id":3,"sLen":0,"time":93085.7142857142,"type":0},{"id":0,"sLen":0,"time":98742.8571428572,"type":0},{"id":2,"sLen":0,"time":98914.2857142857,"type":0},{"id":3,"sLen":0,"time":98914.2857142857,"type":0},{"id":0,"sLen":0,"time":99085.7142857143,"type":0},{"id":1,"sLen":0,"time":99257.1428571429,"type":0},{"id":2,"sLen":0,"time":99257.1428571429,"type":0},{"id":3,"sLen":0,"time":99428.5714285714,"type":0},{"id":0,"sLen":0,"time":99600,"type":0},{"id":1,"sLen":0,"time":99600,"type":0},{"id":3,"sLen":0,"time":99771.4285714286,"type":0},{"id":1,"sLen":0,"time":99942.8571428572,"type":0},{"id":2,"sLen":0,"time":99942.8571428572,"type":0},{"id":0,"sLen":0,"time":100114.285714286,"type":0},{"id":1,"sLen":0,"time":100285.714285714,"type":0},{"id":2,"sLen":0,"time":100285.714285714,"type":0},{"id":3,"sLen":0,"time":100457.142857143,"type":0},{"id":1,"sLen":0,"time":100628.571428571,"type":0},{"id":2,"sLen":0,"time":100628.571428571,"type":0},{"id":3,"sLen":0,"time":100800,"type":0},{"id":0,"sLen":0,"time":100971.428571429,"type":0},{"id":2,"sLen":0,"time":100971.428571429,"type":0},{"id":1,"sLen":0,"time":101142.857142857,"type":0},{"id":2,"sLen":0,"time":101314.285714286,"type":0},{"id":3,"sLen":0,"time":101314.285714286,"type":0},{"id":0,"sLen":0,"time":101485.714285714,"type":0},{"id":1,"sLen":0,"time":101657.142857143,"type":0},{"id":2,"sLen":0,"time":101657.142857143,"type":0},{"id":3,"sLen":0,"time":101828.571428571,"type":0},{"id":1,"sLen":0,"time":102000,"type":0},{"id":2,"sLen":0,"time":102000,"type":0},{"id":0,"sLen":0,"time":102171.428571429,"type":0},{"id":1,"sLen":0,"time":102342.857142857,"type":0},{"id":2,"sLen":0,"time":102342.857142857,"type":0},{"id":3,"sLen":0,"time":102514.285714286,"type":0},{"id":1,"sLen":0,"time":102685.714285714,"type":0},{"id":2,"sLen":0,"time":102685.714285714,"type":0},{"id":3,"sLen":0,"time":102857.142857143,"type":0},{"id":0,"sLen":0,"time":103028.571428571,"type":0},{"id":1,"sLen":0,"time":103200,"type":0},{"id":2,"sLen":0,"time":103371.428571429,"type":0},{"id":3,"sLen":0,"time":103542.857142857,"type":0},{"id":0,"sLen":0,"time":103885.714285714,"type":0},{"id":0,"sLen":0,"time":108342.857142857,"type":0},{"id":0,"sLen":0,"time":108685.714285714,"type":0},{"id":2,"sLen":0,"time":108857.142857143,"type":0},{"id":1,"sLen":0,"time":109114.285714286,"type":0},{"id":0,"sLen":0,"time":109371.428571429,"type":0},{"id":2,"sLen":0,"time":109714.285714286,"type":0},{"id":0,"sLen":0,"time":110057.142857143,"type":0},{"id":1,"sLen":0,"time":110228.571428571,"type":0},{"id":3,"sLen":0,"time":110400,"type":0},{"id":0,"sLen":0,"time":110742.857142857,"type":0},{"id":2,"sLen":0,"time":111085.714285714,"type":0},{"id":1,"sLen":0,"time":111428.571428571,"type":0},{"id":0,"sLen":0,"time":111600,"type":0},{"id":1,"sLen":0,"time":111942.857142857,"type":0},{"id":3,"sLen":0,"time":112114.285714286,"type":0},{"id":2,"sLen":0,"time":112457.142857143,"type":0},{"id":0,"sLen":0,"time":112714.285714286,"type":0},{"id":2,"sLen":0,"time":112971.428571428,"type":0},{"id":3,"sLen":0,"time":113228.571428571,"type":0},{"id":0,"sLen":0,"time":113485.714285714,"type":0},{"id":1,"sLen":0,"time":113657.142857143,"type":0},{"id":2,"sLen":0,"time":113828.571428571,"type":0},{"id":0,"sLen":0,"time":114171.428571428,"type":1},{"id":1,"sLen":0,"time":114171.428571428,"type":0},{"id":1,"sLen":0,"time":114514.285714286,"type":1},{"id":3,"sLen":0,"time":114514.285714286,"type":0},{"id":0,"sLen":0,"time":114857.142857143,"type":0},{"id":2,"sLen":0,"time":114857.142857143,"type":1},{"id":0,"sLen":0,"time":120685.714285714,"type":0},{"id":2,"sLen":0,"time":120857.142857143,"type":0},{"id":0,"sLen":0,"time":120942.857142857,"type":0},{"id":3,"sLen":0,"time":121114.285714286,"type":0},{"id":0,"sLen":0,"time":121200,"type":0},{"id":2,"sLen":0,"time":121371.428571428,"type":0},{"id":0,"sLen":0,"time":121457.142857143,"type":0},{"id":3,"sLen":0,"time":121628.571428571,"type":0},{"id":0,"sLen":0,"time":121714.285714286,"type":0},{"id":0,"sLen":0,"time":121885.714285714,"type":0},{"id":3,"sLen":0,"time":122057.142857143,"type":0},{"id":1,"sLen":0,"time":122228.571428571,"type":0},{"id":3,"sLen":0,"time":122314.285714286,"type":0},{"id":0,"sLen":0,"time":122485.714285714,"type":0},{"id":3,"sLen":0,"time":122571.428571428,"type":0},{"id":1,"sLen":0,"time":122742.857142857,"type":0},{"id":3,"sLen":0,"time":122828.571428571,"type":0},{"id":0,"sLen":0,"time":123000,"type":0},{"id":3,"sLen":0,"time":123085.714285714,"type":0},{"id":3,"sLen":0,"time":123257.142857143,"type":0},{"id":1,"sLen":0,"time":123428.571428571,"type":0},{"id":3,"sLen":0,"time":123600,"type":0},{"id":1,"sLen":0,"time":123685.714285714,"type":0},{"id":0,"sLen":0,"time":123857.142857143,"type":0},{"id":1,"sLen":0,"time":123942.857142857,"type":0},{"id":3,"sLen":0,"time":124114.285714286,"type":0},{"id":1,"sLen":0,"time":124200,"type":0},{"id":0,"sLen":0,"time":124371.428571428,"type":0},{"id":1,"sLen":0,"time":124457.142857143,"type":0},{"id":1,"sLen":0,"time":124628.571428571,"type":0},{"id":2,"sLen":0,"time":124800,"type":0},{"id":0,"sLen":0,"time":124971.428571428,"type":0},{"id":2,"sLen":0,"time":125057.142857143,"type":0},{"id":3,"sLen":0,"time":125228.571428571,"type":0},{"id":0,"sLen":0,"time":125314.285714285,"type":0},{"id":1,"sLen":0,"time":125314.285714285,"type":1},{"id":2,"sLen":0,"time":125314.285714285,"type":1},{"id":0,"sLen":0,"time":131657.142857143,"type":0},{"id":0,"sLen":0,"time":131742.857142857,"type":0},{"id":1,"sLen":0,"time":131828.571428571,"type":0},{"id":3,"sLen":0,"time":132000,"type":0},{"id":1,"sLen":0,"time":132171.428571428,"type":0},{"id":2,"sLen":0,"time":132342.857142857,"type":0},{"id":3,"sLen":0,"time":132342.857142857,"type":0},{"id":2,"sLen":0,"time":132428.571428571,"type":0},{"id":3,"sLen":0,"time":132428.571428571,"type":0},{"id":0,"sLen":0,"time":132514.285714285,"type":0},{"id":3,"sLen":0,"time":132685.714285714,"type":0},{"id":1,"sLen":0,"time":132857.142857143,"type":0},{"id":3,"sLen":0,"time":133028.571428571,"type":0},{"id":3,"sLen":0,"time":133114.285714286,"type":0},{"id":1,"sLen":0,"time":133200,"type":0},{"id":0,"sLen":0,"time":133371.428571428,"type":0},{"id":1,"sLen":0,"time":133542.857142857,"type":0},{"id":2,"sLen":0,"time":133714.285714285,"type":0},{"id":3,"sLen":0,"time":133714.285714285,"type":0},{"id":2,"sLen":0,"time":133800,"type":0},{"id":3,"sLen":0,"time":133800,"type":0},{"id":1,"sLen":0,"time":133885.714285714,"type":0},{"id":3,"sLen":0,"time":134057.142857143,"type":0},{"id":1,"sLen":0,"time":134228.571428571,"type":0},{"id":0,"sLen":0,"time":134400,"type":0},{"id":0,"sLen":0,"time":134485.714285714,"type":0},{"id":1,"sLen":0,"time":134571.428571428,"type":0},{"id":3,"sLen":0,"time":134742.857142857,"type":0},{"id":1,"sLen":0,"time":134914.285714285,"type":0},{"id":2,"sLen":0,"time":135085.714285714,"type":0},{"id":3,"sLen":0,"time":135085.714285714,"type":0},{"id":2,"sLen":0,"time":135171.428571429,"type":0},{"id":3,"sLen":0,"time":135171.428571429,"type":0},{"id":0,"sLen":0,"time":135257.142857143,"type":0},{"id":3,"sLen":0,"time":135428.571428571,"type":0},{"id":1,"sLen":0,"time":135600,"type":0},{"id":3,"sLen":0,"time":135771.428571428,"type":0},{"id":3,"sLen":0,"time":135857.142857143,"type":0},{"id":1,"sLen":0,"time":135942.857142857,"type":0},{"id":0,"sLen":0,"time":136114.285714285,"type":0},{"id":1,"sLen":0,"time":136285.714285714,"type":0},{"id":2,"sLen":0,"time":136457.142857143,"type":0},{"id":3,"sLen":0,"time":136457.142857143,"type":0},{"id":2,"sLen":0,"time":136542.857142857,"type":0},{"id":3,"sLen":0,"time":136542.857142857,"type":0},{"id":1,"sLen":0,"time":136628.571428571,"type":0},{"id":3,"sLen":0,"time":136800,"type":0},{"id":1,"sLen":0,"time":136971.428571428,"type":0},{"id":0,"sLen":0,"time":139885.714285714,"type":0},{"id":1,"sLen":0,"time":140228.571428571,"type":0},{"id":0,"sLen":0,"time":140571.428571428,"type":0},{"id":1,"sLen":0,"time":140742.857142857,"type":0},{"id":3,"sLen":0,"time":141085.714285714,"type":0},{"id":2,"sLen":0,"time":141428.571428571,"type":0},{"id":1,"sLen":0,"time":141771.428571428,"type":0},{"id":2,"sLen":0,"time":141942.857142857,"type":0},{"id":3,"sLen":0,"time":142114.285714285,"type":0},{"id":1,"sLen":0,"time":142285.714285714,"type":0},{"id":2,"sLen":0,"time":145371.428571428,"type":0},{"id":3,"sLen":0,"time":145714.285714286,"type":0},{"id":0,"sLen":0,"time":146057.142857143,"type":0},{"id":1,"sLen":0,"time":146228.571428571,"type":0},{"id":3,"sLen":0,"time":146400,"type":0},{"id":2,"sLen":0,"time":146571.428571428,"type":0},{"id":2,"sLen":0,"time":146914.285714286,"type":0},{"id":3,"sLen":0,"time":147085.714285714,"type":0},{"id":0,"sLen":0,"time":147428.571428571,"type":0},{"id":3,"sLen":0,"time":147771.428571428,"type":0},{"id":0,"sLen":0,"time":150857.142857143,"type":0},{"id":1,"sLen":0,"time":151200,"type":0},{"id":3,"sLen":0,"time":151542.857142857,"type":0},{"id":2,"sLen":0,"time":151885.714285714,"type":0},{"id":0,"sLen":0,"time":152228.571428571,"type":0},{"id":3,"sLen":0,"time":152228.571428571,"type":1},{"id":2,"sLen":0,"time":152571.428571428,"type":0},{"id":0,"sLen":0,"time":152914.285714286,"type":1},{"id":1,"sLen":0,"time":152914.285714286,"type":0},{"id":1,"sLen":0,"time":153085.714285714,"type":0},{"id":3,"sLen":0,"time":153257.142857143,"type":0},{"id":0,"sLen":0,"time":156342.857142857,"type":0},{"id":3,"sLen":0,"time":156685.714285714,"type":0},{"id":2,"sLen":0,"time":156857.142857143,"type":0},{"id":1,"sLen":0,"time":157028.571428571,"type":0},{"id":0,"sLen":0,"time":157200,"type":0},{"id":3,"sLen":0,"time":157371.428571428,"type":0},{"id":1,"sLen":0,"time":157542.857142857,"type":0},{"id":2,"sLen":0,"time":157714.285714286,"type":0},{"id":3,"sLen":0,"time":157714.285714286,"type":0},{"id":0,"sLen":0,"time":157885.714285714,"type":0},{"id":1,"sLen":0,"time":158057.142857143,"type":0},{"id":0,"sLen":0,"time":158400,"type":1},{"id":2,"sLen":0,"time":158400,"type":1},{"id":3,"sLen":257.14285714287,"time":158400,"type":0}],"position":"boyfriend","type":1,"characters":["veethree"]}],"codenameChart":true,"stage":"glitcher","noteTypes":["No Animation"]}