{
    "subtitles": [
      {
        "time": "0:00",
        "text": "โหว้ นายเก่งกว่าที่ฉันคิดไว้นะ."
      },
      {
        "time": "0:03",
        "text": "ฉันนี้ห่วยจริง…"
      },
      {
        "time": "0:07",
        "text": "Beep!"
      },
      {
        "time": "0:09",
        "text": "ให้กำลังใจฉันหรอ?"
      },
      {
        "time": "0:12",
        "text": "*Ay SFX*"
      },
      {
        "time": "0:13",
        "text": "ขอบคุณนะ"
      },
      {
        "time": "0:14",
        "text": ""
      },
      {
        "time": "0:15",
        "text": "นี้อีกสักเพลงมั้ยละ?"
      },
      {
        "time": "0:16",
        "text": "มาเลย!"
      }   
    ]
  }
  